README.md
setup.py
IPChecklists/Checklist.py
IPChecklists/Covers.py
IPChecklists/SolutionPool.py
IPChecklists/__init__.py
IPChecklists/constraints_cplex.py
IPChecklists/constraints_pythonmip.py
IPChecklists/dataset.py
IPChecklists/lr_init.py
IPChecklists/model_cplex.py
IPChecklists/model_pythonmip.py
IPChecklists/utils.py
predictive_checklists.egg-info/PKG-INFO
predictive_checklists.egg-info/SOURCES.txt
predictive_checklists.egg-info/dependency_links.txt
predictive_checklists.egg-info/requires.txt
predictive_checklists.egg-info/top_level.txt