Metadata-Version: 1.2
Name: predictive-checklists
Version: 0.2
Summary: Creating Predictive Checklists Using Integer Programming
Home-page: https://github.com/MLforHealth/predictive_checklists
Author: Haoran Zhang
Author-email: haoranz@mit.edu
License: BSD
Platform: UNKNOWN
Requires-Python: >=3.7
